PyBACCHUS/__init__.py
PyBACCHUS/abu.py
PyBACCHUS/babsma_com.py
PyBACCHUS/bacchus.py
PyBACCHUS/bsyn_com.py
PyBACCHUS/elements_wln.py
PyBACCHUS/eqw.py
PyBACCHUS/eqwidt_com.py
PyBACCHUS/helper_methods.py
PyBACCHUS/init_com.py
PyBACCHUS/linelists.py
PyBACCHUS/par.py
PyBACCHUS/plt.py
PyBACCHUS/results.py
PyBACCHUS/star.py
PyBACCHUS/stellar_parameters.py
PyBACCHUS/tab.py
pybacchus-1.1.0.dist-info/licenses/LICENSE
pybacchus-1.1.0.dist-info/METADATA
pybacchus-1.1.0.dist-info/WHEEL
pybacchus-1.1.0.dist-info/top_level.txt
pybacchus-1.1.0.dist-info/RECORD
