Metadata-Version: 2.4
Name: PyBACCHUS
Version: 1.1.0
Requires-Python: >=3.10
License-File: LICENSE
Requires-Dist: numpy
Requires-Dist: pandas
Requires-Dist: astropy
Requires-Dist: matplotlib
Requires-Dist: sphinx-rtd-theme==3.0.2
Dynamic: license-file
